odoo/addons/purchase_order_line_image/README.rst
odoo/addons/purchase_order_line_image/__init__.py
odoo/addons/purchase_order_line_image/__manifest__.py
odoo/addons/purchase_order_line_image/i18n/it.po
odoo/addons/purchase_order_line_image/i18n/purchase_order_line_image.pot
odoo/addons/purchase_order_line_image/models/__init__.py
odoo/addons/purchase_order_line_image/models/purchase_order.py
odoo/addons/purchase_order_line_image/models/res_config_settings.py
odoo/addons/purchase_order_line_image/readme/DESCRIPTION.rst
odoo/addons/purchase_order_line_image/reports/purchase_order_report.xml
odoo/addons/purchase_order_line_image/static/description/icon.png
odoo/addons/purchase_order_line_image/static/description/index.html
odoo/addons/purchase_order_line_image/tests/__init__.py
odoo/addons/purchase_order_line_image/tests/test_purchase_order.py
odoo/addons/purchase_order_line_image/views/purchase_order_view.xml
odoo/addons/purchase_order_line_image/views/res_config_settings.xml
odoo14_addon_purchase_order_line_image-14.0.1.0.1.dist-info/METADATA
odoo14_addon_purchase_order_line_image-14.0.1.0.1.dist-info/WHEEL
odoo14_addon_purchase_order_line_image-14.0.1.0.1.dist-info/top_level.txt
odoo14_addon_purchase_order_line_image-14.0.1.0.1.dist-info/RECORD
